sage_session/__init__.py
sage_session/admin/__init__.py
sage_session/admin/user_session.py
sage_session/apps.py
sage_session/backends/__init__.py
sage_session/backends/session.py
sage_session/handlers/__init__.py
sage_session/handlers/session.py
sage_session/middleware/__init__.py
sage_session/middleware/session.py
sage_session/middleware/track.py
sage_session/migrations/__init__.py
sage_session/models/__init__.py
sage_session/models/user_session.py
sage_session/templates/user_sessions.html
sage_session/tests/test_backend.py
sage_session/tests/test_handlers.py
sage_session/tests/test_middleware.py
sage_session/tests/test_track.py
sage_session/tests/test_urls.py
sage_session/urls.py
sage_session/views/__init__.py
sage_session/views/session.py
django_sage_session-0.1.5.dist-info/LICENSE
django_sage_session-0.1.5.dist-info/METADATA
django_sage_session-0.1.5.dist-info/WHEEL
django_sage_session-0.1.5.dist-info/RECORD
